issnresolver/__init__.py
issnresolver/core.py
issnresolver/utils.py
issnresolver/version.py
issnresolver-0.1.5.dist-info/licenses/LICENSE
issnresolver-0.1.5.dist-info/METADATA
issnresolver-0.1.5.dist-info/WHEEL
issnresolver-0.1.5.dist-info/top_level.txt
issnresolver-0.1.5.dist-info/RECORD
